setup.cfg
setup.py
nfft/__init__.py
nfft/core.py
nfft/kernels.py
nfft/utils.py
nfft/version.py
nfft.egg-info/PKG-INFO
nfft.egg-info/SOURCES.txt
nfft.egg-info/dependency_links.txt
nfft.egg-info/requires.txt
nfft.egg-info/top_level.txt
nfft/tests/__init__.py
nfft/tests/test_core.py
nfft/tests/test_kernels.py
nfft/tests/test_utils.py