Metadata-Version: 1.1
Name: nfft
Version: 0.1
Summary: nfft: pure-python nonuniform fast Fourier transform
Home-page: http://github.com/jakevdp/nfft/
Author: Jake VanderPlas
Author-email: jakevdp@uw.edu
License: MIT
Platform: OS Independent
Classifier: Development Status :: 3 - Alpha
Classifier: Environment :: Console
Classifier: Intended Audience :: Science/Research
Classifier: License :: OSI Approved :: MIT License
Classifier: Operating System :: OS Independent
Classifier: Programming Language :: Python
Classifier: Topic :: Scientific/Engineering
Requires: numpy
Requires: scipy
Requires: pytest
